vismo/__init__.py
vismo/version.py
vismo-0.0.0.dist-info/LICENSE
vismo-0.0.0.dist-info/METADATA
vismo-0.0.0.dist-info/WHEEL
vismo-0.0.0.dist-info/top_level.txt
vismo-0.0.0.dist-info/RECORD
